py_gnuplot-1.3.2.dist-info/licenses/LICENSE.txt
pygnuplot/__init__.py
pygnuplot/gnuplot.py
pygnuplot/pyplot.py
py_gnuplot-1.3.2.dist-info/METADATA
py_gnuplot-1.3.2.dist-info/WHEEL
py_gnuplot-1.3.2.dist-info/top_level.txt
py_gnuplot-1.3.2.dist-info/RECORD
