Metadata-Version: 2.4
Name: py-gnuplot
Version: 1.3.2
Summary: py-gnuplot is a python plot tools based on gnuplot.
Home-page: http://www.gnuplot.info
Author: Yongping Guo
Author-email: Yongping Guo <guoyoooping@163.com>
License: GPLv3
Keywords: gnuplot,pandas,py-gnuplot
License-File: LICENSE.txt
Requires-Dist: pandas
Dynamic: author
Dynamic: home-page
Dynamic: license-file
